{
  "title": "RC V Accident report",
  "Child's Name": null,
  "Date of Accident": null,
  "Time of Accident": null,
  "Nature of Injury": null,
  "Location of Incident": null,
  "What the child was doing": null,
  "Caregiver response and first aid": null,
  "Name of Caregiver that responded": null,
  "Additional Information": null,
  "Parent contacted?": {
    "Yes": "unselected",
    "No": "unselected"
  },
  "Name of Parent contacted": null,
  "Who contacted parent": null,
  "How parent was contacted": {
    "Phone": "unselected",
    "Email": "unselected",
    "Other": "unselected"
  },
  "Time parent was contacted": null,
  "Other Contacts or Actions": null,
  "signature": null,
  "date": null
}